meerkatbot/__init__.py
meerkatbot/commands.py
meerkatbot/events.py
meerkatbot/exceptions.py
meerkatbot/logger.py
meerkatbot/meerkatbot.py
meerkatbot-0.1.0.6.dist-info/METADATA
meerkatbot-0.1.0.6.dist-info/WHEEL
meerkatbot-0.1.0.6.dist-info/top_level.txt
meerkatbot-0.1.0.6.dist-info/RECORD
