Metadata-Version: 2.1
Name: meerkatbot
Version: 0.1.0.6
Summary: MeerkatBot is an extra layer to discord py
Home-page: https://github.com/lautaumpierrez/meerkatbot.git
Author: Lautaro Umpiérrez
License: MIT
Platform: UNKNOWN
Requires-Dist: discord
Requires-Dist: asyncio
